GmailChecker/GmailChecker.py
GmailChecker/GmailCheckerEnhanced.py
GmailChecker/__init__.py
GmailChecker-1.0.0.dist-info/LICENSE
GmailChecker-1.0.0.dist-info/METADATA
GmailChecker-1.0.0.dist-info/WHEEL
GmailChecker-1.0.0.dist-info/top_level.txt
GmailChecker-1.0.0.dist-info/RECORD
